hiredis/version.py
hiredis/__init__.py
hiredis/hiredis.pyi
hiredis/py.typed
hiredis/hiredis.cpython-39-darwin.so
hiredis-3.3.0.dist-info/RECORD
hiredis-3.3.0.dist-info/WHEEL
hiredis-3.3.0.dist-info/top_level.txt
hiredis-3.3.0.dist-info/METADATA
hiredis-3.3.0.dist-info/licenses/LICENSE
