Metadata-Version: 2.1
Name: hiredis
Version: 3.3.0
Summary: Python wrapper for hiredis
Home-page: https://github.com/redis/hiredis-py
Author: Jan-Erik Rediger, Pieter Noordhuis
Author-email: janerik@fnordig.de, pcnoordhuis@gmail.com
License: MIT
Project-URL: Changes, https://github.com/redis/hiredis-py/releases
Project-URL: Issue tracker, https://github.com/redis/hiredis-py/issues
Keywords: Redis
Classifier: Development Status :: 5 - Production/Stable
Classifier: Intended Audience :: Developers
Classifier: License :: OSI Approved :: MIT License
Classifier: Operating System :: MacOS
Classifier: Operating System :: POSIX
Classifier: Programming Language :: C
Classifier: Programming Language :: Python :: 3
Classifier: Programming Language :: Python :: 3 :: Only
Classifier: Programming Language :: Python :: 3.8
Classifier: Programming Language :: Python :: 3.9
Classifier: Programming Language :: Python :: 3.10
Classifier: Programming Language :: Python :: 3.11
Classifier: Programming Language :: Python :: 3.12
Classifier: Programming Language :: Python :: 3.13
Classifier: Programming Language :: Python :: 3.14
Classifier: Programming Language :: Python :: Implementation :: CPython
Classifier: Topic :: Software Development
Requires-Python: >=3.8
License-File: LICENSE
